renku_r_tools/__init__.py
renku_r_tools/__main__.py
renku_r_tools/packrat.py
renku_r_tools/renv.py
renku_r_tools-0.0.4.dist-info/LICENSE
renku_r_tools-0.0.4.dist-info/METADATA
renku_r_tools-0.0.4.dist-info/WHEEL
renku_r_tools-0.0.4.dist-info/entry_points.txt
renku_r_tools-0.0.4.dist-info/top_level.txt
renku_r_tools-0.0.4.dist-info/RECORD
