Metadata-Version: 2.1
Name: renku-r-tools
Version: 0.0.4
Summary: A toolbox to work with R projects on Renku
Home-page: https://github.com/auwerxlab/renku-r-tools
Author: Laboratory of Integrative System Physiology (LISP) at EPFL
Author-email: alexis.rapin@epfl.ch
License: Apache License 2.0
Download-URL: https://github.com/auwerxlab/renku-r-tools/archive/v0.0.4.tar.gz
Platform: UNKNOWN
Requires-Dist: click (>=7.0)
